pydantic_gubbins/__init__.py
pydantic_gubbins/descriptors.py
pydantic_gubbins/main.py
pydantic_gubbins/test/__init__.py
pydantic_gubbins/test/test_descriptors.py
pydantic_gubbins/test/test_union.py
pydantic_gubbins/typing/__init__.py
pydantic_gubbins/typing/union.py
pydantic_gubbins-1.0.7.dist-info/LICENSE
pydantic_gubbins-1.0.7.dist-info/METADATA
pydantic_gubbins-1.0.7.dist-info/WHEEL
pydantic_gubbins-1.0.7.dist-info/top_level.txt
pydantic_gubbins-1.0.7.dist-info/RECORD
