Metadata-Version: 2.1
Name: pydantic-gubbins
Version: 1.0.7
Summary: Various helpful extensions for working with pydantic
Author-email: Nick Young <nick.young.github@gmail.com>
License: MIT License
Project-URL: homepage, https://github.com/nickyoung-github/pydantic-gubbins
Classifier: License :: OSI Approved :: MIT License
Classifier: Programming Language :: Python :: 3
Classifier: Programming Language :: Python :: 3 :: Only
Classifier: Programming Language :: Python :: 3.11
Classifier: Programming Language :: Python :: 3.12
Classifier: Programming Language :: Python :: 3.13
Classifier: Operating System :: OS Independent
Requires-Python: >=3.11
License-File: LICENSE
Requires-Dist: frozendict
Requires-Dist: pydantic
Requires-Dist: setuptools
Provides-Extra: test
Requires-Dist: pytest; extra == "test"
Requires-Dist: pytest-cov; extra == "test"
